munki_manifest_generator/get_device_catalogs.py
munki_manifest_generator/logger.py
munki_manifest_generator/main.py
munki_manifest_generator/manifest.py
munki_manifest_generator/azstorage/az_storage_actions.py
munki_manifest_generator/azstorage/az_storage_clients.py
munki_manifest_generator/graph/concurrent_batch.py
munki_manifest_generator/graph/get_authentication_token.py
munki_manifest_generator/graph/get_device_group_membership.py
munki_manifest_generator/graph/get_user_group_membership.py
munki_manifest_generator/graph/make_api_request.py
munki_manifest_generator/graph/obtain_access_token.py
Munki_Manifest_Generator-1.2.1.dist-info/LICENSE
Munki_Manifest_Generator-1.2.1.dist-info/METADATA
Munki_Manifest_Generator-1.2.1.dist-info/WHEEL
Munki_Manifest_Generator-1.2.1.dist-info/entry_points.txt
Munki_Manifest_Generator-1.2.1.dist-info/top_level.txt
Munki_Manifest_Generator-1.2.1.dist-info/RECORD
