Metadata-Version: 2.1
Name: Munki-Manifest-Generator
Version: 1.2.1
Summary: Tool to create and update Munki manifests for devices managed in Intune
Home-page: https://github.com/almenscorner/munki-manifest-generator
Author: Tobias Almén
Author-email: almenscorner@outlook.com
Project-URL: Bug Tracker, https://github.com/almenscorner/munki-manifest-generator/issues
Classifier: Programming Language :: Python :: 3
Classifier: License :: OSI Approved :: MIT License
Classifier: Operating System :: OS Independent
Requires-Python: >=3.7
License-File: LICENSE
Requires-Dist: msal>=1.20.0
Requires-Dist: msrest>=0.7.1
Requires-Dist: azure-storage-blob>=12.15.0
Requires-Dist: retrying>=1.3.4
